kaydee/__init__.py
kaydee-0.1.2.dist-info/LICENSE
kaydee-0.1.2.dist-info/METADATA
kaydee-0.1.2.dist-info/WHEEL
kaydee-0.1.2.dist-info/top_level.txt
kaydee-0.1.2.dist-info/RECORD
