Metadata-Version: 2.1
Name: kaydee
Version: 0.1.2
Summary: Bounded kernel density estimation.
Home-page: https://github.com/mdmould/kaydee
Author: Matthew Mould
Author-email: mattdmould@gmail.com
License: MIT
Requires-Python: >=3.7
License-File: LICENSE
Requires-Dist: numpy
Requires-Dist: scipy
Requires-Dist: tqdm-pathos
